image_frequency_analysis/__init__.py
image_frequency_analysis/frequency_analysis.py
image_frequency_analysis-0.2.8.dist-info/LICENSE
image_frequency_analysis-0.2.8.dist-info/METADATA
image_frequency_analysis-0.2.8.dist-info/WHEEL
image_frequency_analysis-0.2.8.dist-info/RECORD
