Metadata-Version: 2.1
Name: image_frequency_analysis
Version: 0.2.8
Summary: A package to perform image frequency analysis using the Fourier Transform method
Home-page: https://github.com/thivagar-manickam/image_frequency_analysis
License: MIT
Keywords: Image Processing,Fourier Transform,Edge Detection,Frequency analysis
Author: M Thivagar
Requires-Python: >=3.8
Classifier: License :: OSI Approved :: MIT License
Classifier: Programming Language :: Python :: 3
Classifier: Programming Language :: Python :: 3.8
Classifier: Programming Language :: Python :: 3.9
Classifier: Programming Language :: Python :: 3.10
Classifier: Programming Language :: Python :: 3.11
Requires-Dist: matplotlib (>=3.5.0)
Requires-Dist: numpy (>=1.21.4)
Requires-Dist: opencv-python (>=4.5.1.48)
Requires-Dist: pandas (>=1.3.5)
Project-URL: Repository, https://github.com/thivagar-manickam/image_frequency_analysis
